jsondaora/__init__.py
jsondaora/dataclasses.py
jsondaora/decorator.py
jsondaora/deserializers.py
jsondaora/exceptions.py
jsondaora/fields.py
jsondaora/py.typed
jsondaora/schema.py
jsondaora/serializers.py
jsondaora/typed_dict.py
jsondaora/tests/test_dataclass.py
jsondaora/tests/test_dataclass_typed_dict.py
jsondaora/tests/test_schema.py
jsondaora/tests/test_serialize.py
jsondaora/tests/test_typed_dict.py
jsondaora-0.14.1.dist-info/LICENSE
jsondaora-0.14.1.dist-info/WHEEL
jsondaora-0.14.1.dist-info/METADATA
jsondaora-0.14.1.dist-info/RECORD
