Metadata-Version: 2.1
Name: jsondaora
Version: 0.14.1
Summary: Interoperates @dataclass with json objects
Home-page: https://github.com/dutradda/jsondaora
License: UNKNOWN
Author: Diogo Dutra
Author-email: diogodutradamata@gmail.com
Requires-Python: >=3.8
Classifier: License :: OSI Approved :: MIT License
Classifier: Development Status :: 1 - Planning
Classifier: Intended Audience :: Developers
Classifier: Programming Language :: Python :: 3.8
Classifier: Topic :: Software Development :: Libraries
Requires-Dist: orjson>=3,<4
Requires-Dist: dictdaora
Requires-Dist: mkdocs ; extra == "doc"
Requires-Dist: mkdocs-material ; extra == "doc"
Requires-Dist: markdown-include ; extra == "doc"
Requires-Dist: black ; extra == "test"
Requires-Dist: bumpversion ; extra == "test"
Requires-Dist: flake8 ; extra == "test"
Requires-Dist: isort ; extra == "test"
Requires-Dist: ipython ; extra == "test"
Requires-Dist: mypy ; extra == "test"
Requires-Dist: pytest-cov ; extra == "test"
Requires-Dist: pytest-mock ; extra == "test"
Requires-Dist: pytest>=5.1.1 ; extra == "test"
Requires-Dist: tox ; extra == "test"
Project-URL: Documentation, https://dutradda.github.io/jsondaora/
Provides-Extra: doc
Provides-Extra: test
